popsy_cli/__init__.py
popsy_cli/analytics.py
popsy_cli/api.py
popsy_cli/dm_automation.py
popsy_cli/main.py
popsy_ai-0.0.8.dist-info/METADATA
popsy_ai-0.0.8.dist-info/WHEEL
popsy_ai-0.0.8.dist-info/entry_points.txt
popsy_ai-0.0.8.dist-info/RECORD
