Metadata-Version: 2.4
Name: popsy-ai
Version: 0.0.8
Summary: Reddit DM automation CLI using Popsy AI for lead generation and outreach
Project-URL: Homepage, https://popsy.ai
Author-email: Popsy AI <support@popsy.ai>
License: Copyright 2025 Popsy Labs, Inc.
Keywords: ai,automation,dm,lead-generation,outreach,reddit
Classifier: Intended Audience :: Developers
Classifier: Intended Audience :: End Users/Desktop
Classifier: License :: Other/Proprietary License
Classifier: Operating System :: OS Independent
Classifier: Programming Language :: Python :: 3
Classifier: Programming Language :: Python :: 3.9
Classifier: Programming Language :: Python :: 3.10
Classifier: Programming Language :: Python :: 3.11
Classifier: Programming Language :: Python :: 3.12
Classifier: Topic :: Communications
Classifier: Topic :: Internet :: WWW/HTTP
Classifier: Topic :: Office/Business
Classifier: Topic :: Software Development :: Libraries :: Python Modules
Requires-Python: >=3.9
Requires-Dist: browserforge>=1.2.3
Requires-Dist: camoufox[geoip]>=0.4.11
Requires-Dist: posthog>=3.1.0
Requires-Dist: requests>=2.31.0
